furiek/__init__.py
furiek/app.py
furiek/exceptions.py
furiek/middleware.py
furiek/request.py
furiek/response.py
furiek/routing.py
furiek/utils.py
furiek-2.0.1.dist-info/licenses/LICENSE
tests/__init__.py
tests/test_app.py
furiek-2.0.1.dist-info/METADATA
furiek-2.0.1.dist-info/WHEEL
furiek-2.0.1.dist-info/top_level.txt
furiek-2.0.1.dist-info/RECORD
