Metadata-Version: 2.4
Name: furiek
Version: 2.0.1
Summary: Современный веб-фреймворк для Python 3.11+ - быстрый, простой и эффективный
Author: Furieks
Author-email: Furieks <furieks@bk.ru>
License: MIT
Project-URL: Homepage, https://github.com/furieks/furiek
Project-URL: Bug Reports, https://github.com/furieks/furiek/issues
Project-URL: Source, https://github.com/furieks/furiek
Keywords: web,framework,asgi,http,api
Classifier: Development Status :: 4 - Beta
Classifier: Intended Audience :: Developers
Classifier: License :: OSI Approved :: MIT License
Classifier: Operating System :: OS Independent
Classifier: Programming Language :: Python :: 3
Classifier: Programming Language :: Python :: 3.11
Classifier: Programming Language :: Python :: 3.12
Classifier: Programming Language :: Python :: 3.13
Classifier: Topic :: Internet :: WWW/HTTP :: Dynamic Content
Classifier: Topic :: Software Development :: Libraries :: Python Modules
Requires-Python: >=3.11
License-File: LICENSE
Requires-Dist: uvicorn>=0.20.0
Dynamic: author
Dynamic: license-file
Dynamic: requires-python
